dmdj/__init__.py
dmdj/makers.py
dmdj/settings.py
dmdj-0.4.2.dist-info/DESCRIPTION.rst
dmdj-0.4.2.dist-info/METADATA
dmdj-0.4.2.dist-info/RECORD
dmdj-0.4.2.dist-info/WHEEL
dmdj-0.4.2.dist-info/metadata.json
dmdj-0.4.2.dist-info/top_level.txt
lib/dmdj/__init__.py
lib/dmdj/makers.py
lib/dmdj/settings.py
