Metadata-Version: 2.0
Name: dmdj
Version: 0.4.2
Summary: Django model generator for JSON metadata
Home-page: https://github.com/chop-dbhi/data-models-django
Author: The Children's Hospital of Philadelphia
Author-email: cbmisupport@email.chop.edu
License: Other/Proprietary
Download-URL: https://github.com/chop-dbhi/data-models-django/tarball/0.4.2
Keywords: healthcare,data models,Django,OMOP,OHDSI,i2b2,PCORnet,PEDSnet
Platform: UNKNOWN
Classifier: Development Status :: 4 - Beta
Classifier: Programming Language :: Python :: 2.7
Classifier: Programming Language :: Python :: 3.4
Classifier: Programming Language :: Python :: 3.5
Classifier: Intended Audience :: Developers
Classifier: Intended Audience :: Science/Research
Classifier: Intended Audience :: Healthcare Industry
Classifier: License :: Other/Proprietary License
Classifier: Topic :: Database
Classifier: Topic :: Software Development :: Libraries :: Python Modules
Classifier: Topic :: Software Development :: Code Generators
Classifier: Natural Language :: English
Requires-Dist: Django (>=1.7,<1.11)
